<?xml version="1.0" encoding="ISO-8859-1"?>
<!DOCTYPE sect1 PUBLIC "-//OASIS//DTD DocBook XML V4.5//EN"
   "http://www.oasis-open.org/docbook/xml/4.5/docbookx.dtd" [
  <!ENTITY % general-entities SYSTEM "../../general.ent">
  %general-entities;

  <!ENTITY elfutils-homepage      "https://fedorahosted.org/elfutils/">
  <!ENTITY elfutils-wikipedia     " ">
  <!ENTITY elfutils-download-http "https://fedorahosted.org/releases/e/l/elfutils/&elfutils-version;/elfutils-&elfutils-version;.tar.bz2">
  <!ENTITY elfutils-download-ftp  "ftp://ftp.oregonstate.edu/pub/blfs/svn/e/elfutils-&elfutils-version;.tar.bz2">
  <!ENTITY elfutils-md5sum        "7527f22dff8b1ac8c122cfc4d3d3bb1e">
  <!ENTITY elfutils-size          "5.2 MB">
  <!ENTITY elfutils-buildsize     "72 MB">
  <!ENTITY elfutils-time          "0.7 SBU">
]>

<sect1 id="elfutils" xreflabel="elfutils-&elfutils-version;">
  <?dbhtml filename="elfutils.html"?>

  <title>elfutils-&elfutils-version;</title>

  <sect2 role="package">
    <title>Introduction</title>

    <para>
      The elfutils package contains set of utilities and libraries for handling
      ELF (Executable and Linkable Format) files.
    </para>

    <bridgehead renderas="sect3">Package Information</bridgehead>
    <itemizedlist spacing="compact">
      <listitem>
        <para>
          Homepage: <ulink url="&elfutils-homepage;"/>
        </para>
      </listitem>
      <listitem>
        <para>
          Wikipedia: <ulink url="&elfutils-wikipedia;"/>
        </para>
      </listitem>
      <listitem>
        <para>
          Download (HTTP): <ulink url="&elfutils-download-http;"/>
        </para>
      </listitem>
      <listitem>
        <para>
          Download (FTP): <ulink url="&elfutils-download-ftp;"/>
        </para>
      </listitem>
      <listitem>
        <para>
          Download MD5 sum: &elfutils-md5sum;
        </para>
      </listitem>
      <listitem>
        <para>
          Download size: &elfutils-size;
        </para>
      </listitem>
      <listitem>
        <para>
          Estimated disk space required: &elfutils-buildsize;
        </para>
      </listitem>
      <listitem>
        <para>
          Estimated build time: &elfutils-time;
        </para>
      </listitem>
    </itemizedlist>

  </sect2>

  <sect2>
    <title>Installation</title>

    <para>
      Install the package by running the following commands:
    </para>

<!-- don't disable static libs, disable-static switch doesn't work anyways -->
<screen><userinput>./configure --prefix=/usr \
            --disable-nls \
            --program-prefix="eu-" &amp;&amp;
make</userinput></screen>

    <para>
      Now, as the <systemitem class="username">root</systemitem> user:
    </para>

<screen role="root"><userinput>make install</userinput></screen>

    <sect3>
      <title>Command Explanations</title>

      <para>
        <parameter>--program-prefix="eu-"</parameter>: This switch renames
        installed programs to avoid conflict with Binutils programs installed in
        LFS.
      </para>

    </sect3>

  </sect2>

  <sect2>
    <title>Contents</title>

    <indexterm zone="elfutils">
      <primary sortas="b-eu-addr2line">eu-addr2line</primary>
    </indexterm>
    <indexterm zone="elfutils">
      <primary sortas="b-eu-ar">eu-ar</primary>
    </indexterm>
    <indexterm zone="elfutils">
      <primary sortas="b-eu-elfcmp">eu-elfcmp</primary>
    </indexterm>
    <indexterm zone="elfutils">
      <primary sortas="b-eu-elflint">eu-elflint</primary>
    </indexterm>
    <indexterm zone="elfutils">
      <primary sortas="b-eu-findtextrel">eu-findtextrel</primary>
    </indexterm>
    <indexterm zone="elfutils">
      <primary sortas="b-eu-ld">eu-ld</primary>
    </indexterm>
    <indexterm zone="elfutils">
      <primary sortas="b-eu-make-debug-archive">eu-make-debug-archive</primary>
    </indexterm>
    <indexterm zone="elfutils">
      <primary sortas="b-eu-nm">eu-nm</primary>
    </indexterm>
    <indexterm zone="elfutils">
      <primary sortas="b-eu-objdump">eu-objdump</primary>
    </indexterm>
    <indexterm zone="elfutils">
      <primary sortas="b-eu-ranlib">eu-ranlib</primary>
    </indexterm>
    <indexterm zone="elfutils">
      <primary sortas="b-eu-readelf">eu-readelf</primary>
    </indexterm>
    <indexterm zone="elfutils">
      <primary sortas="b-eu-size">eu-size</primary>
    </indexterm>
    <indexterm zone="elfutils">
      <primary sortas="b-eu-stack">eu-stack</primary>
    </indexterm>
    <indexterm zone="elfutils">
      <primary sortas="b-eu-strings">eu-strings</primary>
    </indexterm>
    <indexterm zone="elfutils">
      <primary sortas="b-eu-strip">eu-strip</primary>
    </indexterm>
    <indexterm zone="elfutils">
      <primary sortas="b-eu-unstrip">eu-unstrip</primary>
    </indexterm>
    <indexterm zone="elfutils">
      <primary sortas="c-libasm.a">libasm.a</primary>
    </indexterm>
    <indexterm zone="elfutils">
      <primary sortas="c-libasm.so">libasm.so</primary>
    </indexterm>
    <indexterm zone="elfutils">
      <primary sortas="c-libdw.a">libdw.a</primary>
    </indexterm>
    <indexterm zone="elfutils">
      <primary sortas="c-libdw.so">libdw.so</primary>
    </indexterm>
    <indexterm zone="elfutils">
      <primary sortas="c-libebl.a">libebl.a</primary>
    </indexterm>
    <indexterm zone="elfutils">
      <primary sortas="c-libelf.a">libelf.a</primary>
    </indexterm>
    <indexterm zone="elfutils">
      <primary sortas="c-libelf.so">libelf.so</primary>
    </indexterm>

    <para>
      Incomplete list of installed files and directories:
    </para>

<screen><literal>/usr/bin/eu-addr2line
/usr/bin/eu-ar
/usr/bin/eu-elfcmp
/usr/bin/eu-elflint
/usr/bin/eu-findtextrel
/usr/bin/eu-ld
/usr/bin/eu-make-debug-archive
/usr/bin/eu-nm
/usr/bin/eu-objdump
/usr/bin/eu-ranlib
/usr/bin/eu-readelf
/usr/bin/eu-size
/usr/bin/eu-stack
/usr/bin/eu-strings
/usr/bin/eu-strip
/usr/bin/eu-unstrip
/usr/include/dwarf.h
/usr/include/elfutils/
/usr/include/gelf.h
/usr/include/libelf.h
/usr/include/nlist.h
/usr/lib/elfutils/
/usr/lib/libasm.a
/usr/lib/libasm.so
/usr/lib/libdw.a
/usr/lib/libdw.so
/usr/lib/libebl.a
/usr/lib/libelf.a
/usr/lib/libelf.so</literal></screen>

  </sect2>

</sect1>
