<?xml version="1.0" encoding="ISO-8859-1"?>
<!DOCTYPE sect1 PUBLIC "-//OASIS//DTD DocBook XML V4.5//EN"
   "http://www.oasis-open.org/docbook/xml/4.5/docbookx.dtd" [
  <!ENTITY % general-entities SYSTEM "../../general.ent">
  %general-entities;

  <!ENTITY orc-homepage      "http://code.entropywave.com/orc/">
  <!ENTITY orc-wikipedia     " ">
  <!ENTITY orc-download-http
  "http://code.entropywave.com/download/orc/orc-&orc-version;.tar.gz">
  <!ENTITY orc-download-ftp  " ">
  <!ENTITY orc-md5sum        "1a2552e8d127526c48d644fe6437b377">
  <!ENTITY orc-size          "716 KB">
  <!ENTITY orc-buildsize     "22 MB">
  <!ENTITY orc-time          "0.3 SBU">
]>

<sect1 id="orc" xreflabel="ORC-&orc-version;">
  <?dbhtml filename="orc.html"?>

  <title>ORC-&orc-version;</title>

  <sect2 role="package">
    <title>Introduction</title>

    <para>
      ORC, the OIL Runtime Compiler (and OIL stands for Optimized Inner Loops)
      is a just-in-time compiler implemented as a library and set of associated
      tools for compiling and executing simple programs that operate on arrays
      of data.
    </para>

    <bridgehead renderas="sect3">Package Information</bridgehead>
    <itemizedlist spacing="compact">
      <listitem>
        <para>
          Homepage: <ulink url="&orc-homepage;"/>
        </para>
      </listitem>
      <listitem>
        <para>
          Wikipedia: <ulink url="&orc-wikipedia;"/>
        </para>
      </listitem>
      <listitem>
        <para>
          Download (HTTP): <ulink url="&orc-download-http;"/>
        </para>
      </listitem>
      <listitem>
        <para>
          Download (FTP): <ulink url="&orc-download-ftp;"/>
        </para>
      </listitem>
      <listitem>
        <para>
          Download MD5 sum: &orc-md5sum;
        </para>
      </listitem>
      <listitem>
        <para>
          Download size: &orc-size;
        </para>
      </listitem>
      <listitem>
        <para>
          Estimated disk space required: &orc-buildsize;
        </para>
      </listitem>
      <listitem>
        <para>
          Estimated build time: &orc-time;
        </para>
      </listitem>
    </itemizedlist>

  </sect2>

  <sect2>
    <title>Installation</title>

    <para>
      Install orc by running the following commands:
    </para>

<screen><userinput>./configure --prefix=/usr \
            --disable-static &amp;&amp;
make</userinput></screen>

    <para>
      Now, as the <systemitem class="username">root</systemitem> user:
    </para>

<screen role="root"><userinput>make install</userinput></screen>

  </sect2>

  <sect2>
    <title>Contents</title>

    <indexterm zone="orc">
      <primary sortas="b-orc-bugreport">orc-bugreport</primary>
    </indexterm>
    <indexterm zone="orc">
      <primary sortas="b-orcc">orcc</primary>
    </indexterm>
    <indexterm zone="orc">
      <primary sortas="c-liborc-0.4.so">liborc-0.4.so</primary>
    </indexterm>
    <indexterm zone="orc">
      <primary sortas="c-liborc-test-0.4.so">liborc-test-0.4.so</primary>
    </indexterm>

    <para>
      Incomplete list of installed files and directories:
    </para>

<screen><literal>/usr/bin/orc-bugreport
/usr/bin/orcc
/usr/include/orc-0.4/
/usr/lib/liborc-0.4.so
/usr/lib/liborc-test-0.4.so
/usr/lib/pkgconfig/orc-0.4.pc
/usr/share/aclocal/orc.m4</literal></screen>

  </sect2>

</sect1>
