<?xml version="1.0" encoding="ISO-8859-1"?>
<!DOCTYPE sect1 PUBLIC "-//OASIS//DTD DocBook XML V4.5//EN"
   "http://www.oasis-open.org/docbook/xml/4.5/docbookx.dtd" [
  <!ENTITY changelogs  "http://www.linuxfromscratch.org/blfs">
  <!ENTITY % general-entities SYSTEM "../../general.ent">
  %general-entities;
]>

<!-- vim: set expandtab: -->

<sect1 id="changelog" xreflabel="Change Log">
  <?dbhtml filename="changelog.html"?>

  <title>Change Log</title>

  <!-- <para>Please note that the Change Log only lists which editor was
  responsible for putting the changes into SVN; please read the
  <xref linkend="credits"/> page in Chapter 1 for details on
  who wrote what.</para> -->

  <para>Current release: &version; &ndash; &releasedate;</para>

  <itemizedlist>
    <title>Changelog Entries:</title>

<!-- Changelog template

    <listitem>
      <para>MMMM DD{nd,st,th}, YYYY</para>
      <itemizedlist>
        <listitem>
          <para>[name] - Changelog entry.</para>
        </listitem>
        <listitem>
          <para>[name] - Another changelog entry.</para>
        </listitem>
      </itemizedlist>
    </listitem>

-->
    <listitem>
      <para>April 7th, 2015</para>
      <itemizedlist>
        <listitem>
          <para>[upstream] - Update to libpng-1.6.17.</para>
        </listitem>
      </itemizedlist>
    </listitem>

    <listitem>
      <para>April 6th, 2015</para>
      <itemizedlist>
        <listitem>
          <para>[igor] - Added file.</para>
        </listitem>
      </itemizedlist>
    </listitem>

    <listitem>
      <para>April 5th, 2015</para>
      <itemizedlist>
        <listitem>
          <para>[upstream] - Update to imlib2-1.4.7.</para>
        </listitem>
      </itemizedlist>
    </listitem>

    <listitem>
      <para>April 4th, 2015</para>
      <itemizedlist>
        <listitem>
          <para>[upstream] - Update to logrotate-3.9.1.</para>
        </listitem>
        <listitem>
          <para>[upstream] - Update to libreoffice-4.4.2.</para>
        </listitem>
        <listitem>
          <para>[upstream] - Update to setuptools-15.0.</para>
        </listitem>
      </itemizedlist>
    </listitem>

    <listitem>
      <para>April 3rd, 2015</para>
      <itemizedlist>
        <listitem>
          <para>[upstream] - Update to firefox-37.0.1.</para>
        </listitem>
        <listitem>
          <para>[upstream] - Update to mercurial-3.3.3.</para>
        </listitem>
        <listitem>
          <para>[upstream] - Update to ghostscript-9.16.</para>
        </listitem>
        <listitem>
          <para>[upstream] - Update to gnutls-3.3.14.</para>
        </listitem>
      </itemizedlist>
    </listitem>

    <listitem>
      <para>April 2nd, 2015</para>
      <itemizedlist>
        <listitem>
          <para>[upstream] - Update to git-2.3.5.</para>
        </listitem>
        <listitem>
          <para>[upstream] - Update to mpg123-1.22.1.</para>
        </listitem>
        <listitem>
          <para>[upstream] - Update to thunderbird-31.6.0.</para>
        </listitem>
        <listitem>
          <para>[upstream] - Update to subversion-1.8.13.</para>
        </listitem>
      </itemizedlist>
    </listitem>

    <listitem>
      <para>March 31st, 2015</para>
      <itemizedlist>
        <listitem>
          <para>[upstream] - Update to firefox-37.0.</para>
        </listitem>
        <listitem>
          <para>[upstream] - Update to fontforge-20150330.</para>
        </listitem>
      </itemizedlist>
    </listitem>

    <listitem>
      <para>March 30th, 2015</para>
      <itemizedlist>
        <listitem>
          <para>[upstream] - Update to libtasn1-4.4.</para>
        </listitem>
      </itemizedlist>
    </listitem>

    <listitem>
      <para>March 29th, 2015</para>
      <itemizedlist>
        <listitem>
          <para>[upstream] - Update to icu-55.1.</para>
        </listitem>
        <listitem>
          <para>[upstream] - Update to Mesa-10.5.2.</para>
        </listitem>
        <listitem>
          <para>[igor] - Removed openldap.</para>
        </listitem>
        <listitem>
          <para>[igor] - Removed samba.</para>
        </listitem>
        <listitem>
          <para>[igor] - Removed postfix.</para>
        </listitem>
        <listitem>
          <para>[igor] - Removed vlc.</para>
        </listitem>
        <listitem>
          <para>[igor] - Removed libidn.</para>
        </listitem>
      </itemizedlist>
    </listitem>

    <listitem>
      <para>March 28th, 2015</para>
      <itemizedlist>
        <listitem>
          <para>[upstream] - Update to Fontforge-20150228.</para>
        </listitem>
        <listitem>
          <para>[upstream] - Correct tcl sed.</para>
        </listitem>
        <listitem>
          <para>[upstream] - Update to mc-4.8.14.</para>
        </listitem>
        <listitem>
          <para>[upstream] - Update to Unbound-1.5.3.</para>
        </listitem>
      </itemizedlist>
    </listitem>

    <listitem>
      <para>March 27th, 2015</para>
      <itemizedlist>
        <listitem>
          <para>[upstream] - Update to libXfont-1.5.1.</para>
        </listitem>
        <listitem>
          <para>[upstream] - Update to libdrm-2.4.60.</para>
        </listitem>
        <listitem>
          <para>[upstream] - Update to libXdmcp-1.1.2.</para>
        </listitem>
        <listitem>
          <para>[upstream] - Update to wpa_supplicant-2.4.</para>
        </listitem>
        <listitem>
          <para>[upstream] - Update to xf86-input-synaptics-1.8.2.</para>
        </listitem>
        <listitem>
          <para>[upstream] - Update to dhcpcd-6.8.1.</para>
        </listitem>
        <listitem>
          <para>[upstream] - Update to stunnel-5.14.</para>
        </listitem>
      </itemizedlist>
    </listitem>

    <listitem>
      <para>March 26th, 2015</para>
      <itemizedlist>
        <listitem>
          <para>[upstream] - Update to unrar-5.2.7.</para>
        </listitem>
        <listitem>
          <para>[upstream] - Update to Archive::Zip-1.46.</para>
        </listitem>
        <listitem>
          <para>[upstream] - Update to libdvdread-5.0.3.</para>
        </listitem>
        <listitem>
          <para>[upstream] - Update to hicolor-icon-theme-0.15.</para>
        </listitem>
        <listitem>
          <para>[upstream] - Update to LVM2-2.02.118.</para>
        </listitem>
        <listitem>
          <para>[upstream] - Update to php-5.6.7.</para>
        </listitem>
        <listitem>
          <para>[upstream] - Update to dovecot-2.2.16.</para>
        </listitem>
      </itemizedlist>
    </listitem>

    <listitem>
      <para>March 25th, 2015</para>
      <itemizedlist>
        <listitem>
          <para>[upstream] - Update to glibmm-2.44.0.</para>
        </listitem>
        <listitem>
          <para>[upstream] - Update to glib-2.44.0.</para> 
        </listitem>
        <listitem>
          <para>[upstream] - Update to git-2.3.4.</para>
        </listitem>
      </itemizedlist>
    </listitem>

    <listitem>
      <para>March 24th, 2015</para>
      <itemizedlist>
        <listitem>
          <para>[upstream] - Update to libreoffice-4.4.1.2.</para>
        </listitem>
        <listitem>
          <para>[upstream] - Update to atk-2.16.0.</para>
        </listitem>
      </itemizedlist>
    </listitem>

    <listitem>
      <para>March 23rd, 2015</para>
      <itemizedlist>
        <listitem>
          <para>[upstream] - Update to Setuptools-14.3.1.</para>
        </listitem>
        <listitem>
          <para>[upstream] - Update to dhcp-4.3.2.</para>
        </listitem>
        <listitem>
          <para>[upstream] - Update to nss-3.18.</para>
        </listitem>
        <listitem>
          <para>[upstream] - Update to gparted-0.22.0.</para>
        </listitem>
        <listitem>
          <para>[upstream] - Update to stunnel-5.13.</para>
        </listitem>
        <listitem>
          <para>[upstream] - Update to Wireshark-1.12.4.</para>
        </listitem>
        <listitem>
          <para>[upstream] - Update to Libpcap-1.7.2.</para>
        </listitem>
        <listitem>
          <para>[upstream] - Update to libva-1.5.1 / libva-intel-driver-1.5.1.</para>
        </listitem>
        <listitem>
          <para>[upstream] - Update to mariadb-10.0.17.</para>
        </listitem>
        <listitem>
          <para>[upstream] - Update to sudo-1.8.13.</para>
        </listitem>
        <listitem>
          <para>[upstream] - Update to harfbuzz-0.9.40.</para>
        </listitem>
      </itemizedlist>
    </listitem>

    <listitem>
      <para>March 22nd, 2015</para>
      <itemizedlist>
        <listitem>
          <para>[upstream] - Update to firefox-36.0.4.</para>
        </listitem>
        <listitem>
          <para>[igor] - Update to git-2.3.3.</para>
        </listitem>
        <listitem>
          <para>[igor] - Update to libwebp-0.4.3.</para>
        </listitem>
        <listitem>
          <para>[upstream] - Update to ImageMagick-6.9.1-0.</para>
        </listitem>
        <listitem>
          <para>[igor] - Update to qemu-2.2.1.</para>
        </listitem>
      </itemizedlist>
    </listitem>

    <listitem>
      <para>March 21st, 2015</para>
      <itemizedlist>
        <listitem>
          <para>[upstream] - Update to openssh-6.8p1.</para>
        </listitem>
        <listitem>
          <para>[upstream] - Update to freeglut-3.0.0.</para>
        </listitem>
        <listitem>
          <para>[upstream] - Update to talloc-2.1.2.</para>
        </listitem>
        <listitem>
          <para>[upstream] - Update to poppler-0.32.0.</para>
        </listitem>
      </itemizedlist>
    </listitem>

    <listitem>
      <para>March 20th, 2015</para>
      <itemizedlist>
        <listitem>
          <para>[upstream] - Update to gptfdisk-1.0.0.</para>
        </listitem>
        <listitem>
          <para>[igor] - Removed epdfview.</para>
        </listitem>
      </itemizedlist>
    </listitem>

    <listitem>
      <para>March 19th, 2015</para>
      <itemizedlist>
        <listitem>
          <para>[upstream] - Update to cups-filters-1.0.67.</para>
        </listitem>
        <listitem>
          <para>[upstream] - Update to mercurial-3.3.2.</para>
        </listitem>
        <listitem>
          <para>[upstream] - libtiff - incorporate existing sed and nine
          upstream patches into a consolidated patch.</para>
        </listitem>
        <listitem>
          <para>[upstream] - Update to tcl-8.6.4/tk-8.6.4.</para>
        </listitem>
        <listitem>
          <para>[igor] - Update to ffmpeg-2.6.1.</para>
        </listitem>
        <listitem>
          <para>[igor] - Update to fdk-aac-0.1.4.</para>
        </listitem>
      </itemizedlist>
    </listitem>

    <listitem>
      <para>March 17th, 2015</para>
      <itemizedlist>
        <listitem>
          <para>[igor] - Update to unbound-1.5.2.</para>
        </listitem>
        <listitem>
          <para>[upstream] - Update to libvdpau-1.1.</para>
        </listitem>
        <listitem>
          <para>[upstream] - Update to libXvMC-1.0.9.</para>
        </listitem>
        <listitem>
          <para>[upstream] - Update to Setuptools-14.3.</para>
        </listitem>
      </itemizedlist>
    </listitem>

    <listitem>
      <para>March 16th, 2015</para>
      <itemizedlist>
        <listitem>
          <para>[upstream] - Update to mousepad-0.4.0.</para>
        </listitem>
      </itemizedlist>
    </listitem>

    <listitem>
      <para>March 15th, 2015</para>
      <itemizedlist>
        <listitem>
          <para>[upstream] - Update to libvdpau-1.0.</para>
        </listitem>
        <listitem>
          <para>[upstream] - Update to libX11-1.6.3.</para>
        </listitem>
        <listitem>
          <para>[upstream] - Update to libevdev-1.4.</para>
        </listitem>
        <listitem>
          <para>[upstream] - Update to libgcrypt-1.6.3.</para>
        </listitem>
        <listitem>
          <para>[upstream] - Update to libXxf86vm-1.1.4.</para>
        </listitem>
        <listitem>
          <para>[upstream] - Update to Mesa-10.5.1.</para>
        </listitem>
        <listitem>
          <para>[upstream] - Add Setuptools-14.1.1 and Mako-1.0.1
          Python modules, as they are needed by Mesa-10.5.1.</para>
        </listitem>
        <listitem>
          <para>[igor] - Update to firefox-36.0.1.</para>
        </listitem>
        <listitem>
          <para>[igor] - Update to alsa-utils-1.0.29.</para>
        </listitem>
        <listitem>
          <para>[igor] - Update to libvorbis-1.3.5.</para>
        </listitem>
        <listitem>
          <para>[igor] - Update to alsa-lib-1.0.29.</para>
        </listitem>
        <listitem>
          <para>[igor] - Update to gtk+-2.24.27.</para>
        </listitem>
        <listitem>
          <para>[igor] - Update to randrproto-1.4.1.</para>
        </listitem>
        <listitem>
          <para>[igor] - Update to nasm-2.11.08.</para>
        </listitem>
        <listitem>
          <para>[igor] - Update to cairo-1.14.2.</para>
        </listitem>
        <listitem>
          <para>[igor] - Removed multi_c_rehash.</para>
        </listitem>
        <listitem>
          <para>[igor] - Update to libressl-2.1.4.</para>
        </listitem>
      </itemizedlist>
    </listitem>

    <listitem>
      <para>March 14th, 2015</para>
      <itemizedlist>
        <listitem>
          <para>[upstream] - Updated libsigc++ to 2.4.1.</para>
        </listitem>
      </itemizedlist>
    </listitem>

    <listitem>
      <para>March 13th, 2015</para>
      <itemizedlist>
        <listitem>
          <para>[upstream] - Update cmake to 3.2.1.</para>
        </listitem>
        <listitem>
          <para>[upstream] - Update harfbuzz to 0.9.39.</para>
        </listitem>
        <listitem>
          <para>[upstream] - Update GLib to 2.42.2.</para>
        </listitem>
        <listitem>
          <para>[upstream] - Update libtasn1 to 4.3.</para>
        </listitem>
        <listitem>
          <para>[upstream] - Update p7zip to 9.38.1.</para>
        </listitem>
      </itemizedlist>
    </listitem>

    <listitem>
      <para>March 11th, 2015</para>
      <itemizedlist>
        <listitem>
          <para>[upstream] - Update to Ruby-2.2.1.</para>
        </listitem>
        <listitem>
          <para>[upstream] - Update to intltool-0.51.0.</para>
        </listitem>
      </itemizedlist>
    </listitem>

    <listitem>
      <para>March 10th, 2015</para>
      <itemizedlist>
        <listitem>
          <para>[upstream] - Add libcdio-0.93.</para>
        </listitem>
      </itemizedlist>
    </listitem>

    <listitem>
      <para>March 9th, 2015</para>
      <itemizedlist>
        <listitem>
          <para>[upstream] - Update to git-2.3.2.</para>
        </listitem>
        <listitem>
          <para>[upstream] - Update to curl-7.41.0.</para>
        </listitem>
        <listitem>
          <para>[upstream] - Update to gnutls-3.3.13.</para>
        </listitem>
      </itemizedlist>
    </listitem>

    <listitem>
      <para>March 8th, 2015</para>
      <itemizedlist>
        <listitem>
          <para>[upstream] - Update to LVM2-2.02.117.</para>
        </listitem>
        <listitem>
          <para>[upstream] - Update to patch-2.7.5.</para>
        </listitem>
      </itemizedlist>
    </listitem>

    <listitem>
      <para>March 6th, 2015</para>
      <itemizedlist>
        <listitem>
          <para>[upstream] - BLFS-7.7 released.</para>
        </listitem>
      </itemizedlist>
    </listitem>

  </itemizedlist>

</sect1>
