<?xml version="1.0" encoding="ISO-8859-1"?>
<!DOCTYPE sect1 PUBLIC "-//OASIS//DTD DocBook XML V4.5//EN"
   "http://www.oasis-open.org/docbook/xml/4.5/docbookx.dtd" [
  <!ENTITY % general-entities SYSTEM "../../general.ent">
  %general-entities;

  <!ENTITY gsl-homepage      "http://www.gnu.org/software/gsl/">
  <!ENTITY gsl-wikipedia     "https://en.wikipedia.org/wiki/GNU_Scientific_Library">
  <!ENTITY gsl-download-http "http://ftp.gnu.org/pub/gnu/gsl/gsl-&gsl-version;.tar.gz">
  <!ENTITY gsl-download-ftp  "ftp://ftp.gnu.org/pub/gnu/gsl/gsl-&gsl-version;.tar.gz">
  <!ENTITY gsl-md5sum        "ae44cdfed78ece40e73411b63a78c375">
  <!ENTITY gsl-size          "3.4 MB">
  <!ENTITY gsl-buildsize     "195 MB">
  <!ENTITY gsl-time          "1.5 SBU">
]>

<sect1 id="gsl" xreflabel="GSL-&gsl-version;">
  <?dbhtml filename="gsl.html"?>

  <title>GSL-&gsl-version;</title>

  <sect2 role="package">
    <title>Introduction</title>

    <para>
      The GNU Scientific Library (GSL) is a numerical library for C and C++
      programmers. It provides a wide range of mathematical routines such as
      random number generators, special functions and least-squares fitting.
    </para>

    <bridgehead renderas="sect3">Package Information</bridgehead>
    <itemizedlist spacing="compact">
      <listitem>
        <para>
          Homepage: <ulink url="&gsl-homepage;"/>
        </para>
      </listitem>
      <listitem>
        <para>
          Wikipedia: <ulink url="&gsl-wikipedia;"/>
        </para>
      </listitem>
      <listitem>
        <para>
          Download (HTTP): <ulink url="&gsl-download-http;"/>
        </para>
      </listitem>
      <listitem>
        <para>
          Download (FTP): <ulink url="&gsl-download-ftp;"/>
        </para>
      </listitem>
      <listitem>
        <para>
          Download MD5 sum: &gsl-md5sum;
        </para>
      </listitem>
      <listitem>
        <para>
          Download size: &gsl-size;
        </para>
      </listitem>
      <listitem>
        <para>
          Estimated disk space required: &gsl-buildsize;
        </para>
      </listitem>
      <listitem>
        <para>
          Estimated build time: &gsl-time;
        </para>
      </listitem>
    </itemizedlist>
  </sect2>

  <sect2>
    <title>Installation</title>

    <para>
      Install GSL by running the following commands:
    </para>

<screen><userinput>./configure --prefix=/usr \
            --disable-static &amp;&amp;
make</userinput></screen>

    <para>
      Now, as the <systemitem class="username">root</systemitem> user:
    </para>

<screen role="root"><userinput>make install</userinput></screen>
  </sect2>

  <sect2>
    <title>Contents</title>

    <indexterm zone="gsl">
      <primary sortas="b-gsl-config">gsl-config</primary>
    </indexterm>
    <indexterm zone="gsl">
      <primary sortas="b-gsl-histogram">gsl-histogram</primary>
    </indexterm>
    <indexterm zone="gsl">
      <primary sortas="b-gsl-randist">gsl-randist</primary>
    </indexterm>
    <indexterm zone="gsl">
      <primary sortas="c-libgslcblas.so">libgslcblas.so</primary>
    </indexterm>
    <indexterm zone="gsl">
      <primary sortas="c-libgsl.so">libgsl.so</primary>
    </indexterm>

    <para>
      Incomplete list of installed files and directories:
    </para>

<screen><literal>/usr/bin/gsl-config
/usr/bin/gsl-histogram
/usr/bin/gsl-randist
/usr/include/gsl/
/usr/lib/libgslcblas.so
/usr/lib/libgsl.so
/usr/lib/pkgconfig/gsl.pc
/usr/share/aclocal/gsl.m4
/usr/share/man/man1/gsl-config.1
/usr/share/man/man1/gsl-histogram.1
/usr/share/man/man1/gsl-randist.1
/usr/share/man/man3/gsl.3</literal></screen>

  </sect2>

</sect1>
