<?xml version="1.0" encoding="ISO-8859-1"?>
<!DOCTYPE sect1 PUBLIC "-//OASIS//DTD DocBook XML V4.5//EN"
   "http://www.oasis-open.org/docbook/xml/4.5/docbookx.dtd" [
  <!ENTITY % general-entities SYSTEM "../../general.ent">
  %general-entities;

  <!ENTITY libxxf86misc-homepage      " ">
  <!ENTITY libxxf86misc-wikipedia     " ">
  <!ENTITY libxxf86misc-download-http "&xorg-download-http;/lib/libXxf86misc-&libxxf86misc-version;.tar.bz2">
  <!ENTITY libxxf86misc-download-ftp  "&xorg-download-ftp;/lib/libXxf86misc-&libxxf86misc-version;.tar.bz2">
  <!ENTITY libxxf86misc-md5sum        "6bc0bf78909fd71021c466c793d4385c">
  <!ENTITY libxxf86misc-size          "250 KB">
  <!ENTITY libxxf86misc-buildsize     "2.0 MB">
  <!ENTITY libxxf86misc-time          "0.1 SBU">
]>

<sect1 id="libxxf86misc" xreflabel="libXxf86misc-&libxxf86misc-version;">
  <?dbhtml filename="libxxf86misc.html"?>

  <title>libXxf86misc-&libxxf86misc-version;</title>

  <sect2 role="package">
    <title>Introduction</title>

    <para>
      libXxf86misc provides an interface to the XFree86-Misc extension, which
      allows client applications to query the current keyboard and mouse
      settings of the running XFree86-based (XFree86, Xorg) server.
    </para>

    <bridgehead renderas="sect3">Package Information</bridgehead>
    <itemizedlist spacing="compact">
      <listitem>
        <para>
          Homepage: <ulink url="&libxxf86misc-homepage;"/>
        </para>
      </listitem>
      <listitem>
        <para>
          Wikipedia: <ulink url="&libxxf86misc-wikipedia;"/>
        </para>
      </listitem>
      <listitem>
        <para>
          Download (HTTP): <ulink url="&libxxf86misc-download-http;"/>
        </para>
      </listitem>
      <listitem>
        <para>
          Download (FTP): <ulink url="&libxxf86misc-download-ftp;"/>
        </para>
      </listitem>
      <listitem>
        <para>
          Download MD5 sum: &libxxf86misc-md5sum;
        </para>
      </listitem>
      <listitem>
        <para>
          Download size: &libxxf86misc-size;
        </para>
      </listitem>
      <listitem>
        <para>
          Estimated disk space required: &libxxf86misc-buildsize;
        </para>
      </listitem>
      <listitem>
        <para>
          Estimated build time: &libxxf86misc-time;
        </para>
      </listitem>
    </itemizedlist>

    <bridgehead renderas="sect3">Dependencies</bridgehead>

    <bridgehead renderas="sect4">Required</bridgehead>
    <para>
      <xref linkend="xf86miscproto"/> and
      <xref linkend="libxext"/>
    </para>

  </sect2>

  <sect2>
    <title>Installation</title>

    <para>
      Install the package by running the following commands:
    </para>

<screen><userinput>./configure $XORG_CONFIG &amp;&amp;
make</userinput></screen>

    <para>
      Now, as the <systemitem class="username">root</systemitem> user:
    </para>

<screen role="root"><userinput>make install</userinput></screen>

  </sect2>

  <sect2>
    <title>Contents</title>

    <indexterm zone="libxxf86misc">
      <primary sortas="c-libXxf86misc.so">libXxf86misc.so</primary>
    </indexterm>

    <para>
      Incomplete list of installed files and directories:
    </para>

<screen><literal>/usr/lib/libXxf86misc.so
/usr/lib/pkgconfig/xxf86misc.pc
/usr/share/man/man3/XF86Misc*.3</literal></screen>

  </sect2>

</sect1>
