<?xml version="1.0" encoding="ISO-8859-1"?>
<!DOCTYPE sect1 PUBLIC "-//OASIS//DTD DocBook XML V4.5//EN"
   "http://www.oasis-open.org/docbook/xml/4.5/docbookx.dtd" [
  <!ENTITY % general-entities SYSTEM "../../general.ent">
  %general-entities;

  <!ENTITY zip-homepage      "http://www.info-zip.org/Zip.html">
  <!ENTITY zip-wikipedia     "http://en.wikipedia.org/wiki/Info-ZIP">
  <!ENTITY zip-download-http "&sourceforge-repo;/infozip/zip30.tar.gz">
  <!ENTITY zip-download-ftp  "ftp://ftp.info-zip.org/pub/infozip/src/zip30.tgz">
  <!ENTITY zip-md5sum        "7b74551e63f8ee6aab6fbc86676c0d37">
  <!ENTITY zip-size          "1.1 MB">
  <!ENTITY zip-buildsize     "6.4 MB">
  <!ENTITY zip-time          "0.1 SBU">
]>

<sect1 id="zip" xreflabel="Zip-&zip-version;">
  <?dbhtml filename="zip.html"?>

  <title>Zip-&zip-version;</title>

  <sect2 role="package">
    <title>Introduction</title>

    <para>
      The Zip package contains Zip/application> utilities. These are useful for
      compressing files into <filename>ZIP</filename> archives.
    </para>

    <bridgehead renderas="sect3">Package Information</bridgehead>
    <itemizedlist spacing="compact">
      <listitem>
        <para>
          Homepage: <ulink url="&zip-homepage;"/>
        </para>
      </listitem>
      <listitem>
        <para>
          Wikipedia: <ulink url="&zip-wikipedia;"/>
        </para>
      </listitem>
      <listitem>
        <para>
          Download (HTTP): <ulink url="&zip-download-http;"/>
        </para>
      </listitem>
      <listitem>
        <para>
          Download (FTP): <ulink url="&zip-download-ftp;"/>
        </para>
      </listitem>
      <listitem>
        <para>
          Download MD5 sum: &zip-md5sum;
        </para>
      </listitem>
      <listitem>
        <para>
          Download size: &zip-size;
        </para>
      </listitem>
      <listitem>
        <para>
          Estimated disk space required: &zip-buildsize;
        </para>
      </listitem>
      <listitem>
        <para>
          Estimated build time: &zip-time;
        </para>
      </listitem>
    </itemizedlist>

  </sect2>

  <sect2>
    <title>Installation</title>

    <para>
      Install Zip by running the following commands:
    </para>

<screen><userinput>make -f unix/Makefile generic_gcc</userinput></screen>

    <para>
      Now, as the <systemitem class="username">root</systemitem> user:
    </para>

<screen role="root"><userinput>make prefix=/usr \
     MANDIR=/usr/share/man/man1 -f unix/Makefile install</userinput></screen>

    <sect3>
      <title>Command Explanations</title>

      <para>
        <command>make prefix=/usr -f unix/Makefile install</command>: This
        command overrides the <varname>prefix</varname> variable that is set to
        <filename class='directory'>/usr/local</filename> in the
        <filename>unix/Makefile</filename>. Alternatives to
        <option>generic_gcc</option> can be seen with a <command>make -f
        unix/Makefile list</command> command.
      </para>

    </sect3>

  </sect2>

  <sect2>
    <title>Contents</title>

    <indexterm zone="zip">
      <primary sortas="b-zip">zip</primary>
    </indexterm>
    <indexterm zone="zip">
      <primary sortas="b-zipcloak">zipcloak</primary>
    </indexterm>
    <indexterm zone="zip">
      <primary sortas="b-zipnote">zipnote</primary>
    </indexterm>
    <indexterm zone="zip">
      <primary sortas="b-zipsplit">zipsplit</primary>
    </indexterm>

    <para>
      Incomplete list of installed files and directories:
    </para>

<screen><literal>/usr/bin/zip
/usr/bin/zipcloak
/usr/bin/zipnote
/usr/bin/zipsplit
/usr/share/man/man1/zip.1
/usr/share/man/man1/zipcloak.1
/usr/share/man/man1/zipnote.1
/usr/share/man/man1/zipsplit.1</literal></screen>

  </sect2>

</sect1>
